assignment_4/Untitled Folder/fir.v
`define width 8
module booth_enc(
                  //Output
                  e,
                  //Inputs
                  a, b_seg
                  );
   input [`width-1:0]         a;
   input [2:0]                b_seg; 
   output [2*`width-1:0]      e;
   
   reg [2*`width-1:0]        e;
   always @ (a, b_seg)
     begin
        
        case(b_seg)
          3'b001:
            assign e = {{`width{a[`width-1]}}, a};
          3'b010:
            assign e = {{`width{a[`width-1]}}, a};
          3'b011:
            assign e = {{`width{a[`width-1]}}, a} << 1;
          3'b100:
            assign e = ~({{`width{a[`width-1]}}, a} << 1) + 1;
          3'b101:
            assign e = ~({{`width{a[`width-1]}}, a}) + 1;
          3'b110:
            assign e = ~({{`width{a[`width-1]}}, a}) + 1;
          default:
            assign e = 0;
        endcase // case (b_seg)
    
     end // always @ (a, b_seg)
   
endmodule // booth_enc


module booth_mult(
                  //Output
                  p,
                  //Inputs
                  a, b
                  );
   input [`width-1:0]       a, b;
   output [2*`width-1:0]    p; 

   wire [2*`width-1:0]        c0, c1, c2, c3;
   wire [2*`width-1:0]         p;

   
   booth_enc e0(
                c0,
                a,
                {b[1:0],1'b0}
                );
   booth_enc e1(
                c1,
                a,
                b[3:1]
                );
   booth_enc e2(
                c2,
                a,
                b[5:3]
                );
   booth_enc e3(
                c3,
                a,
                b[7:5]
                );
   assign p = c0 + (c1<<2) + (c2<<4) + (c3<<6);
   
endmodule // booth_mult


module fir(
           //Outputs
           outp,
           //Inputs
           clk, reset, inp);
   input [`width-1:0]      inp;
   input                   clk, reset;
   output [`width-1:0]     outp;

   reg [`width-1:0]        outp;
   reg [`width-1:0]        holderBefore[15:0];
   wire [2*`width-1:0]     sums[15:0];
   reg [19:0]              total;
   
   
   parameter coeffs0=8'b00000010;
   parameter coeffs1=8'b11111111;
   parameter coeffs2=8'b11111100;
   parameter coeffs3=8'b11111010;
   parameter coeffs4=8'b11111110;
   parameter coeffs5=8'b00001010;
   parameter coeffs6=8'b00011010;
   parameter coeffs7=8'b00100101;
   parameter coeffs8=8'b00100101;
   parameter coeffs9=8'b00011010;
   parameter coeffs10=8'b00001010;
   parameter coeffs11=8'b11111110;
   parameter coeffs12=8'b11111010;
   parameter coeffs13=8'b11111100;
   parameter coeffs14=8'b11111111;
   parameter coeffs15=8'b00000010;
   

   booth_mult mult0(sums[0], coeffs0, holderBefore[0]);
   booth_mult mult1(sums[1], coeffs1, holderBefore[1]);
   booth_mult mult2(sums[2], coeffs2, holderBefore[2]);
   booth_mult mult3(sums[3], coeffs3, holderBefore[3]);
   booth_mult mult4(sums[4], coeffs4, holderBefore[4]);
   booth_mult mult5(sums[5], coeffs5, holderBefore[5]);
   booth_mult mult6(sums[6], coeffs6, holderBefore[6]);
   booth_mult mult7(sums[7], coeffs7, holderBefore[7]);
   booth_mult mult8(sums[8], coeffs8, holderBefore[8]);
   booth_mult mult9(sums[9], coeffs9, holderBefore[9]);
   booth_mult mult10(sums[10], coeffs10, holderBefore[10]);
   booth_mult mult11(sums[11], coeffs11, holderBefore[11]);
   booth_mult mult12(sums[12], coeffs12, holderBefore[12]);
   booth_mult mult13(sums[13], coeffs13, holderBefore[13]);
   booth_mult mult14(sums[14], coeffs14, holderBefore[14]);
   booth_mult mult15(sums[15], coeffs15, holderBefore[15]);
   
   always @ (posedge clk, posedge reset)
     begin
        if(reset)
          begin
             holderBefore[0] <= 0;
             holderBefore[1] <= 0;
             holderBefore[2] <= 0;
             holderBefore[3] <= 0;
             holderBefore[4] <= 0;
             holderBefore[5] <= 0;
             holderBefore[6] <= 0;
             holderBefore[7] <= 0;
             holderBefore[8] <= 0;
             holderBefore[9] <= 0;
             holderBefore[10] <= 0;
             holderBefore[11] <= 0;
             holderBefore[12] <= 0;
             holderBefore[13] <= 0;
             holderBefore[14] <= 0;
             holderBefore[15] <= 0;
             outp <= 0;
          end // if (reset)
        else
          begin
             holderBefore[0] <= inp;
             holderBefore[1] <= holderBefore[0];
             holderBefore[2] <= holderBefore[1];
             holderBefore[3] <= holderBefore[2];
             holderBefore[4] <= holderBefore[3];
             holderBefore[5] <= holderBefore[4];
             holderBefore[6] <= holderBefore[5];
             holderBefore[7] <= holderBefore[6];
             holderBefore[8] <= holderBefore[7];
             holderBefore[9] <= holderBefore[8];
             holderBefore[10] <= holderBefore[9];
             holderBefore[11] <= holderBefore[10];
             holderBefore[12] <= holderBefore[11];
             holderBefore[13] <= holderBefore[12];
             holderBefore[14] <= holderBefore[13];
             holderBefore[15] <= holderBefore[14];

             total <= ({{4{sums[0][15]}},sums[0]}+{{4{sums[1][15]}},sums[1]}+{{4{sums[2][15]}},sums[2]}+{{4{sums[3][15]}},sums[3]}+{{4{sums[4][15]}},sums[4]}+{{4{sums[5][15]}},sums[5]}+{{4{sums[6][15]}},sums[6]}+{{4{sums[7][15]}},sums[7]}+{{4{sums[8][15]}},sums[8]}+{{4{sums[9][15]}},sums[9]}+{{4{sums[10][15]}},sums[10]}+{{4{sums[11][15]}},sums[11]}+{{4{sums[12][15]}},sums[12]}+{{4{sums[13][15]}},sums[13]}+{{4{sums[14][15]}},sums[14]}+{{4{sums[15][15]}},sums[15]});
             outp <= total[14:7]; //sign extension and add all the terms of convolution.
             
           end // else: !if(reset)
     end // always @ (posedge clk, posedge reset)
endmodule // fir

assignment_4/Untitled Folder/fir_tb.v
module fir_tb();
    
    reg  [7:0] binary_in[0:255];
    reg  [7:0] binary_out[0:255];
    wire [7:0] outp;
    reg  [7:0] inp;
    reg  [7:0] exp_out;
    reg  [7:0] i;
    reg  reset;
    reg  clk;
    
    initial begin
	$dumpfile("fir.vcd");
	$dumpvars(0, fir_tb);
        i  <= 0;
        clk  <= 0;
        reset  <= 1;
        #50 reset <= 0;
	
        $readmemb("input.list", binary_in);
        $readmemb("output.list", binary_out);

	#3000 $finish;
    end
    
    always #5 clk = ~clk;
    
    fir f1(outp,clk,reset,inp);
    
    always @(posedge clk) begin
       if(reset == 0)begin
          inp     <= binary_in[i];
          exp_out <= binary_out[i];
          i       <= i+1;
       end
    end

endmodule

assignment_4/Untitled Folder/fir.vcd
$date
	Tue Mar 18 10:23:25 2014
$end
$version
	Icarus Verilog
$end
$timescale
	1s
$end
$scope module fir_tb $end
$var wire 8 ! outp [7:0] $end
$var reg 1 " clk $end
$var reg 8 # exp_out [7:0] $end
$var reg 8 $ i [7:0] $end
$var reg 8 % inp [7:0] $end
$var reg 1 & reset $end
$scope module f1 $end
$var wire 1 ' clk $end
$var wire 8 ( inp [7:0] $end
$var wire 1 ) reset $end
$var reg 8 * outp [7:0] $end
$var reg 20 + total [19:0] $end
$scope module mult0 $end
$var wire 8 , a [7:0] $end
$var wire 8 - b [7:0] $end
$var wire 16 . c0 [15:0] $end
$var wire 16 / c1 [15:0] $end
$var wire 16 0 c2 [15:0] $end
$var wire 16 1 c3 [15:0] $end
$var wire 16 2 p [15:0] $end
$scope module e0 $end
$var wire 8 3 a [7:0] $end
$var wire 3 4 b_seg [2:0] $end
$var reg 16 5 e [15:0] $end
$upscope $end
$scope module e1 $end
$var wire 8 6 a [7:0] $end
$var wire 3 7 b_seg [2:0] $end
$var reg 16 8 e [15:0] $end
$upscope $end
$scope module e2 $end
$var wire 8 9 a [7:0] $end
$var wire 3 : b_seg [2:0] $end
$var reg 16 ; e [15:0] $end
$upscope $end
$scope module e3 $end
$var wire 8 < a [7:0] $end
$var wire 3 = b_seg [2:0] $end
$var reg 16 > e [15:0] $end
$upscope $end
$upscope $end
$scope module mult1 $end
$var wire 8 ? a [7:0] $end
$var wire 8 @ b [7:0] $end
$var wire 16 A c0 [15:0] $end
$var wire 16 B c1 [15:0] $end
$var wire 16 C c2 [15:0] $end
$var wire 16 D c3 [15:0] $end
$var wire 16 E p [15:0] $end
$scope module e0 $end
$var wire 8 F a [7:0] $end
$var wire 3 G b_seg [2:0] $end
$var reg 16 H e [15:0] $end
$upscope $end
$scope module e1 $end
$var wire 8 I a [7:0] $end
$var wire 3 J b_seg [2:0] $end
$var reg 16 K e [15:0] $end
$upscope $end
$scope module e2 $end
$var wire 8 L a [7:0] $end
$var wire 3 M b_seg [2:0] $end
$var reg 16 N e [15:0] $end
$upscope $end
$scope module e3 $end
$var wire 8 O a [7:0] $end
$var wire 3 P b_seg [2:0] $end
$var reg 16 Q e [15:0] $end
$upscope $end
$upscope $end
$scope module mult2 $end
$var wire 8 R a [7:0] $end
$var wire 8 S b [7:0] $end
$var wire 16 T c0 [15:0] $end
$var wire 16 U c1 [15:0] $end
$var wire 16 V c2 [15:0] $end
$var wire 16 W c3 [15:0] $end
$var wire 16 X p [15:0] $end
$scope module e0 $end
$var wire 8 Y a [7:0] $end
$var wire 3 Z b_seg [2:0] $end
$var reg 16 [ e [15:0] $end
$upscope $end
$scope module e1 $end
$var wire 8 \ a [7:0] $end
$var wire 3 ] b_seg [2:0] $end
$var reg 16 ^ e [15:0] $end
$upscope $end
$scope module e2 $end
$var wire 8 _ a [7:0] $end
$var wire 3 ` b_seg [2:0] $end
$var reg 16 a e [15:0] $end
$upscope $end
$scope module e3 $end
$var wire 8 b a [7:0] $end
$var wire 3 c b_seg [2:0] $end
$var reg 16 d e [15:0] $end
$upscope $end
$upscope $end
$scope module mult3 $end
$var wire 8 e a [7:0] $end
$var wire 8 f b [7:0] $end
$var wire 16 g c0 [15:0] $end
$var wire 16 h c1 [15:0] $end
$var wire 16 i c2 [15:0] $end
$var wire 16 j c3 [15:0] $end
$var wire 16 k p [15:0] $end
$scope module e0 $end
$var wire 8 l a [7:0] $end
$var wire 3 m b_seg [2:0] $end
$var reg 16 n e [15:0] $end
$upscope $end
$scope module e1 $end
$var wire 8 o a [7:0] $end
$var wire 3 p b_seg [2:0] $end
$var reg 16 q e [15:0] $end
$upscope $end
$scope module e2 $end
$var wire 8 r a [7:0] $end
$var wire 3 s b_seg [2:0] $end
$var reg 16 t e [15:0] $end
$upscope $end
$scope module e3 $end
$var wire 8 u a [7:0] $end
$var wire 3 v b_seg [2:0] $end
$var reg 16 w e [15:0] $end
$upscope $end
$upscope $end
$scope module mult4 $end
$var wire 8 x a [7:0] $end
$var wire 8 y b [7:0] $end
$var wire 16 z c0 [15:0] $end
$var wire 16 { c1 [15:0] $end
$var wire 16 | c2 [15:0] $end
$var wire 16 } c3 [15:0] $end
$var wire 16 ~ p [15:0] $end
$scope module e0 $end
$var wire 8 !" a [7:0] $end
$var wire 3 "" b_seg [2:0] $end
$var reg 16 #" e [15:0] $end
$upscope $end
$scope module e1 $end
$var wire 8 $" a [7:0] $end
$var wire 3 %" b_seg [2:0] $end
$var reg 16 &" e [15:0] $end
$upscope $end
$scope module e2 $end
$var wire 8 '" a [7:0] $end
$var wire 3 (" b_seg [2:0] $end
$var reg 16 )" e [15:0] $end
$upscope $end
$scope module e3 $end
$var wire 8 *" a [7:0] $end
$var wire 3 +" b_seg [2:0] $end
$var reg 16 ," e [15:0] $end
$upscope $end
$upscope $end
$scope module mult5 $end
$var wire 8 -" a [7:0] $end
$var wire 8 ." b [7:0] $end
$var wire 16 /" c0 [15:0] $end
$var wire 16 0" c1 [15:0] $end
$var wire 16 1" c2 [15:0] $end
$var wire 16 2" c3 [15:0] $end
$var wire 16 3" p [15:0] $end
$scope module e0 $end
$var wire 8 4" a [7:0] $end
$var wire 3 5" b_seg [2:0] $end
$var reg 16 6" e [15:0] $end
$upscope $end
$scope module e1 $end
$var wire 8 7" a [7:0] $end
$var wire 3 8" b_seg [2:0] $end
$var reg 16 9" e [15:0] $end
$upscope $end
$scope module e2 $end
$var wire 8 :" a [7:0] $end
$var wire 3 ;" b_seg [2:0] $end
$var reg 16 <" e [15:0] $end
$upscope $end
$scope module e3 $end
$var wire 8 =" a [7:0] $end
$var wire 3 >" b_seg [2:0] $end
$var reg 16 ?" e [15:0] $end
$upscope $end
$upscope $end
$scope module mult6 $end
$var wire 8 @" a [7:0] $end
$var wire 8 A" b [7:0] $end
$var wire 16 B" c0 [15:0] $end
$var wire 16 C" c1 [15:0] $end
$var wire 16 D" c2 [15:0] $end
$var wire 16 E" c3 [15:0] $end
$var wire 16 F" p [15:0] $end
$scope module e0 $end
$var wire 8 G" a [7:0] $end
$var wire 3 H" b_seg [2:0] $end
$var reg 16 I" e [15:0] $end
$upscope $end
$scope module e1 $end
$var wire 8 J" a [7:0] $end
$var wire 3 K" b_seg [2:0] $end
$var reg 16 L" e [15:0] $end
$upscope $end
$scope module e2 $end
$var wire 8 M" a [7:0] $end
$var wire 3 N" b_seg [2:0] $end
$var reg 16 O" e [15:0] $end
$upscope $end
$scope module e3 $end
$var wire 8 P" a [7:0] $end
$var wire 3 Q" b_seg [2:0] $end
$var reg 16 R" e [15:0] $end
$upscope $end
$upscope $end
$scope module mult7 $end
$var wire 8 S" a [7:0] $end
$var wire 8 T" b [7:0] $end
$var wire 16 U" c0 [15:0] $end
$var wire 16 V" c1 [15:0] $end
$var wire 16 W" c2 [15:0] $end
$var wire 16 X" c3 [15:0] $end
$var wire 16 Y" p [15:0] $end
$scope module e0 $end
$var wire 8 Z" a [7:0] $end
$var wire 3 [" b_seg [2:0] $end
$var reg 16 \" e [15:0] $end
$upscope $end
$scope module e1 $end
$var wire 8 ]" a [7:0] $end
$var wire 3 ^" b_seg [2:0] $end
$var reg 16 _" e [15:0] $end
$upscope $end
$scope module e2 $end
$var wire 8 `" a [7:0] $end
$var wire 3 a" b_seg [2:0] $end
$var reg 16 b" e [15:0] $end
$upscope $end
$scope module e3 $end
$var wire 8 c" a [7:0] $end
$var wire 3 d" b_seg [2:0] $end
$var reg 16 e" e [15:0] $end
$upscope $end
$upscope $end
$scope module mult8 $end
$var wire 8 f" a [7:0] $end
$var wire 8 g" b [7:0] $end
$var wire 16 h" c0 [15:0] $end
$var wire 16 i" c1 [15:0] $end
$var wire 16 j" c2 [15:0] $end
$var wire 16 k" c3 [15:0] $end
$var wire 16 l" p [15:0] $end
$scope module e0 $end
$var wire 8 m" a [7:0] $end
$var wire 3 n" b_seg [2:0] $end
$var reg 16 o" e [15:0] $end
$upscope $end
$scope module e1 $end
$var wire 8 p" a [7:0] $end
$var wire 3 q" b_seg [2:0] $end
$var reg 16 r" e [15:0] $end
$upscope $end
$scope module e2 $end
$var wire 8 s" a [7:0] $end
$var wire 3 t" b_seg [2:0] $end
$var reg 16 u" e [15:0] $end
$upscope $end
$scope module e3 $end
$var wire 8 v" a [7:0] $end
$var wire 3 w" b_seg [2:0] $end
$var reg 16 x" e [15:0] $end
$upscope $end
$upscope $end
$scope module mult9 $end
$var wire 8 y" a [7:0] $end
$var wire 8 z" b [7:0] $end
$var wire 16 {" c0 [15:0] $end
$var wire 16 |" c1 [15:0] $end
$var wire 16 }" c2 [15:0] $end
$var wire 16 ~" c3 [15:0] $end
$var wire 16 !# p [15:0] $end
$scope module e0 $end
$var wire 8 "# a [7:0] $end
$var wire 3 ## b_seg [2:0] $end
$var reg 16 $# e [15:0] $end
$upscope $end
$scope module e1 $end
$var wire 8 %# a [7:0] $end
$var wire 3 &# b_seg [2:0] $end
$var reg 16 '# e [15:0] $end
$upscope $end
$scope module e2 $end
$var wire 8 (# a [7:0] $end
$var wire 3 )# b_seg [2:0] $end
$var reg 16 *# e [15:0] $end
$upscope $end
$scope module e3 $end
$var wire 8 +# a [7:0] $end
$var wire 3 ,# b_seg [2:0] $end
$var reg 16 -# e [15:0] $end
$upscope $end
$upscope $end
$scope module mult10 $end
$var wire 8 .# a [7:0] $end
$var wire 8 /# b [7:0] $end
$var wire 16 0# c0 [15:0] $end
$var wire 16 1# c1 [15:0] $end
$var wire 16 2# c2 [15:0] $end
$var wire 16 3# c3 [15:0] $end
$var wire 16 4# p [15:0] $end
$scope module e0 $end
$var wire 8 5# a [7:0] $end
$var wire 3 6# b_seg [2:0] $end
$var reg 16 7# e [15:0] $end
$upscope $end
$scope module e1 $end
$var wire 8 8# a [7:0] $end
$var wire 3 9# b_seg [2:0] $end
$var reg 16 :# e [15:0] $end
$upscope $end
$scope module e2 $end
$var wire 8 ;# a [7:0] $end
$var wire 3 <# b_seg [2:0] $end
$var reg 16 =# e [15:0] $end
$upscope $end
$scope module e3 $end
$var wire 8 ># a [7:0] $end
$var wire 3 ?# b_seg [2:0] $end
$var reg 16 @# e [15:0] $end
$upscope $end
$upscope $end
$scope module mult11 $end
$var wire 8 A# a [7:0] $end
$var wire 8 B# b [7:0] $end
$var wire 16 C# c0 [15:0] $end
$var wire 16 D# c1 [15:0] $end
$var wire 16 E# c2 [15:0] $end
$var wire 16 F# c3 [15:0] $end
$var wire 16 G# p [15:0] $end
$scope module e0 $end
$var wire 8 H# a [7:0] $end
$var wire 3 I# b_seg [2:0] $end
$var reg 16 J# e [15:0] $end
$upscope $end
$scope module e1 $end
$var wire 8 K# a [7:0] $end
$var wire 3 L# b_seg [2:0] $end
$var reg 16 M# e [15:0] $end
$upscope $end
$scope module e2 $end
$var wire 8 N# a [7:0] $end
$var wire 3 O# b_seg [2:0] $end
$var reg 16 P# e [15:0] $end
$upscope $end
$scope module e3 $end
$var wire 8 Q# a [7:0] $end
$var wire 3 R# b_seg [2:0] $end
$var reg 16 S# e [15:0] $end
$upscope $end
$upscope $end
$scope module mult12 $end
$var wire 8 T# a [7:0] $end
$var wire 8 U# b [7:0] $end
$var wire 16 V# c0 [15:0] $end
$var wire 16 W# c1 [15:0] $end
$var wire 16 X# c2 [15:0] $end
$var wire 16 Y# c3 [15:0] $end
$var wire 16 Z# p [15:0] $end
$scope module e0 $end
$var wire 8 [# a [7:0] $end
$var wire 3 \# b_seg [2:0] $end
$var reg 16 ]# e [15:0] $end
$upscope $end
$scope module e1 $end
$var wire 8 ^# a [7:0] $end
$var wire 3 _# b_seg [2:0] $end
$var reg 16 `# e [15:0] $end
$upscope $end
$scope module e2 $end
$var wire 8 a# a [7:0] $end
$var wire 3 b# b_seg [2:0] $end
$var reg 16 c# e [15:0] $end
$upscope $end
$scope module e3 $end
$var wire 8 d# a [7:0] $end
$var wire 3 e# b_seg [2:0] $end
$var reg 16 f# e [15:0] $end
$upscope $end
$upscope $end
$scope module mult13 $end
$var wire 8 g# a [7:0] $end
$var wire 8 h# b [7:0] $end
$var wire 16 i# c0 [15:0] $end
$var wire 16 j# c1 [15:0] $end
$var wire 16 k# c2 [15:0] $end
$var wire 16 l# c3 [15:0] $end
$var wire 16 m# p [15:0] $end
$scope module e0 $end
$var wire 8 n# a [7:0] $end
$var wire 3 o# b_seg [2:0] $end
$var reg 16 p# e [15:0] $end
$upscope $end
$scope module e1 $end
$var wire 8 q# a [7:0] $end
$var wire 3 r# b_seg [2:0] $end
$var reg 16 s# e [15:0] $end
$upscope $end
$scope module e2 $end
$var wire 8 t# a [7:0] $end
$var wire 3 u# b_seg [2:0] $end
$var reg 16 v# e [15:0] $end
$upscope $end
$scope module e3 $end
$var wire 8 w# a [7:0] $end
$var wire 3 x# b_seg [2:0] $end
$var reg 16 y# e [15:0] $end
$upscope $end
$upscope $end
$scope module mult14 $end
$var wire 8 z# a [7:0] $end
$var wire 8 {# b [7:0] $end
$var wire 16 |# c0 [15:0] $end
$var wire 16 }# c1 [15:0] $end
$var wire 16 ~# c2 [15:0] $end
$var wire 16 !$ c3 [15:0] $end
$var wire 16 "$ p [15:0] $end
$scope module e0 $end
$var wire 8 #$ a [7:0] $end
$var wire 3 $$ b_seg [2:0] $end
$var reg 16 %$ e [15:0] $end
$upscope $end
$scope module e1 $end
$var wire 8 &$ a [7:0] $end
$var wire 3 '$ b_seg [2:0] $end
$var reg 16 ($ e [15:0] $end
$upscope $end
$scope module e2 $end
$var wire 8 )$ a [7:0] $end
$var wire 3 *$ b_seg [2:0] $end
$var reg 16 +$ e [15:0] $end
$upscope $end
$scope module e3 $end
$var wire 8 ,$ a [7:0] $end
$var wire 3 -$ b_seg [2:0] $end
$var reg 16 .$ e [15:0] $end
$upscope $end
$upscope $end
$scope module mult15 $end
$var wire 8 /$ a [7:0] $end
$var wire 8 0$ b [7:0] $end
$var wire 16 1$ c0 [15:0] $end
$var wire 16 2$ c1 [15:0] $end
$var wire 16 3$ c2 [15:0] $end
$var wire 16 4$ c3 [15:0] $end
$var wire 16 5$ p [15:0] $end
$scope module e0 $end
$var wire 8 6$ a [7:0] $end
$var wire 3 7$ b_seg [2:0] $end
$var reg 16 8$ e [15:0] $end
$upscope $end
$scope module e1 $end
$var wire 8 9$ a [7:0] $end
$var wire 3 :$ b_seg [2:0] $end
$var reg 16 ;$ e [15:0] $end
$upscope $end
$scope module e2 $end
$var wire 8 <$ a [7:0] $end
$var wire 3 =$ b_seg [2:0] $end
$var reg 16 >$ e [15:0] $end
$upscope $end
$scope module e3 $end
$var wire 8 ?$ a [7:0] $end
$var wire 3 @$ b_seg [2:0] $end
$var reg 16 A$ e [15:0] $end
$upscope $end
$upscope $end
$upscope $end
$upscope $end
$enddefinitions $end
#0
$dumpvars
b0 A$
b0 @$
b10 ?$
b0 >$
b0 =$
b10 <$
b0 ;$
b0 :$
b10 9$
b0 8$
b0 7$
b10 6$
b0 5$
b0 4$
b0 3$
b0 2$
b0 1$
b0 0$
b10 /$
b0 .$
b0 -$
b11111111 ,$
b0 +$
b0 *$
b11111111 )$
b0 ($
b0 '$
b11111111 &$
b0 %$
b0 $$
b11111111 #$
b0 "$
b0 !$
b0 ~#
b0 }#
b0 |#
b0 {#
b11111111 z#
b0 y#
b0 x#
b11111100 w#
b0 v#
b0 u#
b11111100 t#
b0 s#
b0 r#
b11111100 q#
b0 p#
b0 o#
b11111100 n#
b0 m#
b0 l#
b0 k#
b0 j#
b0 i#
b0 h#
b11111100 g#
b0 f#
b0 e#
b11111010 d#
b0 c#
b0 b#
b11111010 a#
b0 `#
b0 _#
b11111010 ^#
b0 ]#
b0 \#
b11111010 [#
b0 Z#
b0 Y#
b0 X#
b0 W#
b0 V#
b0 U#
b11111010 T#
b0 S#
b0 R#
b11111110 Q#
b0 P#
b0 O#
b11111110 N#
b0 M#
b0 L#
b11111110 K#
b0 J#
b0 I#
b11111110 H#
b0 G#
b0 F#
b0 E#
b0 D#
b0 C#
b0 B#
b11111110 A#
b0 @#
b0 ?#
b1010 >#
b0 =#
b0 <#
b1010 ;#
b0 :#
b0 9#
b1010 8#
b0 7#
b0 6#
b1010 5#
b0 4#
b0 3#
b0 2#
b0 1#
b0 0#
b0 /#
b1010 .#
b0 -#
b0 ,#
b11010 +#
b0 *#
b0 )#
b11010 (#
b0 '#
b0 &#
b11010 %#
b0 $#
b0 ##
b11010 "#
b0 !#
b0 ~"
b0 }"
b0 |"
b0 {"
b0 z"
b11010 y"
b0 x"
b0 w"
b100101 v"
b0 u"
b0 t"
b100101 s"
b0 r"
b0 q"
b100101 p"
b0 o"
b0 n"
b100101 m"
b0 l"
b0 k"
b0 j"
b0 i"
b0 h"
b0 g"
b100101 f"
b0 e"
b0 d"
b100101 c"
b0 b"
b0 a"
b100101 `"
b0 _"
b0 ^"
b100101 ]"
b0 \"
b0 ["
b100101 Z"
b0 Y"
b0 X"
b0 W"
b0 V"
b0 U"
b0 T"
b100101 S"
b0 R"
b0 Q"
b11010 P"
b0 O"
b0 N"
b11010 M"
b0 L"
b0 K"
b11010 J"
b0 I"
b0 H"
b11010 G"
b0 F"
b0 E"
b0 D"
b0 C"
b0 B"
b0 A"
b11010 @"
b0 ?"
b0 >"
b1010 ="
b0 <"
b0 ;"
b1010 :"
b0 9"
b0 8"
b1010 7"
b0 6"
b0 5"
b1010 4"
b0 3"
b0 2"
b0 1"
b0 0"
b0 /"
b0 ."
b1010 -"
b0 ,"
b0 +"
b11111110 *"
b0 )"
b0 ("
b11111110 '"
b0 &"
b0 %"
b11111110 $"
b0 #"
b0 ""
b11111110 !"
b0 ~
b0 }
b0 |
b0 {
b0 z
b0 y
b11111110 x
b0 w
b0 v
b11111010 u
b0 t
b0 s
b11111010 r
b0 q
b0 p
b11111010 o
b0 n
b0 m
b11111010 l
b0 k
b0 j
b0 i
b0 h
b0 g
b0 f
b11111010 e
b0 d
b0 c
b11111100 b
b0 a
b0 `
b11111100 _
b0 ^
b0 ]
b11111100 \
b0 [
b0 Z
b11111100 Y
b0 X
b0 W
b0 V
b0 U
b0 T
b0 S
b11111100 R
b0 Q
b0 P
b11111111 O
b0 N
b0 M
b11111111 L
b0 K
b0 J
b11111111 I
b0 H
b0 G
b11111111 F
b0 E
b0 D
b0 C
b0 B
b0 A
b0 @
b11111111 ?
b0 >
b0 =
b10 <
b0 ;
b0 :
b10 9
b0 8
b0 7
b10 6
b0 5
b0 4
b10 3
b0 2
b0 1
b0 0
b0 /
b0 .
b0 -
b10 ,
bx +
b0 *
1)
bx (
0'
1&
bx %
b0 $
bx #
0"
b0 !
$end
#5
1"
1'
#10
0"
0'
#15
1"
1'
#20
0"
0'
#25
1"
1'
#30
0"
0'
#35
1"
1'
#40
0"
0'
#45
1"
1'
#50
0&
0)
0"
0'
#55
b0 5
b0 8
b0 ;
b0 >
bx0 4
bx 7
bx :
bx =
bx *
bx !
b0 +
bx -
b1 $
b0 #
b0 %
b0 (
1"
1'
#60
0"
0'
#65
b0 H
b0 K
b0 N
b0 Q
b0 5
b0 8
b0 ;
b0 >
bx0 G
bx J
bx M
bx P
b0 4
b0 7
b0 :
b0 =
b0 *
b0 !
bx @
b0 -
b10 $
b11111110 #
b1010100 %
b1010100 (
1"
1'
#70
0"
0'
#75
b10101000 2
b0 [
b0 ^
b0 a
b0 d
b0 H
b0 K
b0 N
b0 Q
b10 8
b10 /
b10 ;
b10 0
b10 >
b10 1
bx0 Z
bx ]
bx `
bx c
b0 G
b0 J
b0 M
b0 P
b10 7
b10 :
b10 =
bx S
b0 @
b1010100 -
b11 $
b1 #
b1010 %
b1010 (
1"
1'
#80
0"
0'
#85
b1111111110101100 E
b0 n
b0 q
b0 t
b0 w
b0 [
b0 ^
b0 a
b0 d
b1111111111111111 K
b1111111111111111 B
b1111111111111111 N
b1111111111111111 C
b1111111111111111 Q
b1111111111111111 D
b1111111111111100 5
b10100 2
b1111111111111100 .
b1111111111111110 8
b1111111111111110 /
b10 ;
b0 >
b0 1
bx0 m
bx p
bx s
bx v
b0 Z
b0 ]
b0 `
b0 c
b10 J
b10 M
b10 P
b100 4
b101 7
b1 :
b0 =
b10101000 +
bx f
b0 S
b1010100 @
b1010 -
b100 $
b11 #
b1101 %
b1101 (
1"
1'
#90
0"
0'
#95
b1111111010110000 X
b0 #"
b0 &"
b0 )"
b0 ,"
b0 n
b0 q
b0 t
b0 w
b1111111111111100 ^
b1111111111111100 U
b1111111111111100 a
b1111111111111100 V
b1111111111111100 d
b1111111111111100 W
b10 H
b1111111111110110 E
b10 A
b1 K
b1 B
b1111111111111111 N
b0 Q
b0 D
b10 5
b11010 2
b10 .
b1111111111111110 8
bx0 ""
bx %"
bx ("
bx +"
b0 m
b0 p
b0 s
b0 v
b10 ]
b10 `
b10 c
b100 G
b101 J
b1 M
b0 P
b10 4
b110 7
b1 *
b1 !
b11111111111111000000 +
bx y
b0 f
b1010100 S
b1010 @
b1101 -
b101 $
b0 #
b1111000 %
b1111000 (
1"
1'
#100
0"
0'
#105
b1111111000001000 k
b0 6"
b0 9"
b0 <"
b0 ?"
b0 #"
b0 &"
b0 )"
b0 ,"
b1111111111111010 q
b1111111111111010 h
b1111111111111010 t
b1111111111111010 i
b1111111111111010 w
b1111111111111010 j
b1000 [
b1111111111011000 X
b1000 T
b100 ^
b100 U
b1111111111111100 a
b0 d
b0 W
b1111111111111111 H
b1111111111110011 E
b1111111111111111 A
b1 K
b0 5
b11110000 2
b0 .
b1111111111111100 8
b1111111111111100 /
b0 ;
b0 0
b100 >
b100 1
bx0 5"
bx 8"
bx ;"
bx >"
b0 ""
b0 %"
b0 ("
b0 +"
b10 p
b10 s
b10 v
b100 Z
b101 ]
b1 `
b0 c
b10 G
b110 J
b0 4
b100 7
b111 :
b11 =
b11111111 *
b11111111 !
b11111111111011000000 +
bx ."
b0 y
b1010100 f
b1010 S
b1101 @
b1111000 -
b110 $
b11111010 #
b1001011 %
b1001011 (
1"
1'
#110
0"
0'
#115
b1111111101011000 ~
b0 I"
b0 L"
b0 O"
b0 R"
b0 6"
b0 9"
b0 <"
b0 ?"
b1111111111111110 &"
b1111111111111110 {
b1111111111111110 )"
b1111111111111110 |
b1111111111111110 ,"
b1111111111111110 }
b1100 n
b1111111111000100 k
b1100 g
b110 q
b110 h
b1111111111111010 t
b0 w
b0 j
b1111111111111100 [
b1111111111001100 X
b1111111111111100 T
b100 ^
b0 H
b1111111110001000 E
b0 A
b10 K
b10 B
b0 N
b0 C
b1111111111111110 Q
b1111111111111110 D
b1111111111111110 5
b10010110 2
b1111111111111110 .
b1111111111111110 8
b1111111111111110 /
b10 ;
b10 0
b10 >
b10 1
bx0 H"
bx K"
bx N"
bx Q"
b0 5"
b0 8"
b0 ;"
b0 >"
b10 %"
b10 ("
b10 +"
b100 m
b101 p
b1 s
b0 v
b10 Z
b110 ]
b0 G
b100 J
b111 M
b11 P
b110 4
b101 7
b1 :
b10 =
b11111101 *
b11111101 !
b11111111111011000011 +
bx A"
b0 ."
b1010100 y
b1010 f
b1101 S
b1111000 @
b1001011 -
b111 $
b11111011 #
b11110011 %
b11110011 (
1"
1'
#120
0"
0'
