assignment_4/working/fir/fir.v
module booth_encoder (
	//	Outputs
	PP,
	// 	Input
	A, B_segment
	);
	input 	[7:0] 	A;
	input 	[2:0] 	B_segment;
	output	[15:0]	PP;
	reg 	[15:0]	PP;
	reg 	[15:0]	A_extended;

	always @ (A or B_segment) begin
		A_extended = {{8{A[7]}},A};	
		case (B_segment)
			3'b000,3'b111: 	PP<= 0;
			3'b001,3'b010: 	PP<= A_extended;
			3'b101,3'b110: 	PP<= (-A_extended);
			3'b011:		PP<= (A_extended<<1);
			3'b100:		PP<= (-A_extended<<1);
		endcase
	end
endmodule

module booth_mult(
	//	Outputs
	p,
	//	Inputs
	a, b
	);
	input 	[7:0]	a,b;
	output 	[15:0]	p;
	reg 	[15:0]	p;
	wire	[15:0]	PP1,PP2,PP3,PP4;
	booth_encoder booth1(PP1,a,{b[1],b[0],1'b0});
	booth_encoder booth2(PP2,a,{b[3],b[2],b[1]});
	booth_encoder booth3(PP3,a,{b[5],b[4],b[3]});
	booth_encoder booth4(PP4,a,{b[7],b[6],b[5]});	
	always @ (PP1 or PP2 or PP3 or PP4) begin
		p = PP1 + (PP2<<2) + (PP3<<4) + (PP4<<6);
	end
endmodule

module fir(
			clk,
			reset,
			inp,
			outp
		  );
	input			reset,clk;
	input	[7:0]	inp;
	output	[7:0]	outp;
	reg		[7:0]	outp;
	reg		[7:0]	inp_list[13:0];
	wire	[15:0]	PA[13:0];
	reg		[7:0]	h[13:0];
	reg		[19:0]	outp_temp;

	always @ (posedge clk, posedge reset) begin
		h[0] <=   8'b00000000;
		h[1] <=   8'b11111011;
		h[2] <=   8'b11111011;
		h[3] <=   8'b11111111;
		h[4] <=   8'b00001010;
		h[5] <=   8'b00011001;
		h[6] <=   8'b00100100;
		h[7] <=   8'b00100100;
		h[8] <=   8'b00011001;
		h[9] <=   8'b00001010;
		h[10] <=  8'b11111111;
		h[11] <=  8'b11111011;
		h[12] <=  8'b11111011;
		h[13] <=  8'b00000000;
	end

	always @ (posedge clk, posedge reset) begin
	if (reset) begin
		inp_list[13] <= 0;
		inp_list[12] <= 0;
		inp_list[11] <= 0;
		inp_list[10] <= 0;
		inp_list[9] <= 0;
		inp_list[8] <= 0;
		inp_list[7] <= 0;
		inp_list[6] <= 0;
		inp_list[5] <= 0;
		inp_list[4] <= 0;
		inp_list[3] <= 0;
		inp_list[2] <= 0;
		inp_list[1] <= 0;
		inp_list[0] <= 0;
	end else begin
		inp_list[13] <= inp_list[12];
		inp_list[12] <= inp_list[11];
		inp_list[11] <= inp_list[10];
		inp_list[10] <= inp_list[9];
		inp_list[9] <= inp_list[8];
		inp_list[8] <= inp_list[7];
		inp_list[7] <= inp_list[6];
		inp_list[6] <= inp_list[5];
		inp_list[5] <= inp_list[4];
		inp_list[4] <= inp_list[3];
		inp_list[3] <= inp_list[2];
		inp_list[2] <= inp_list[1];
		inp_list[1] <= inp_list[0];
		inp_list[0] <= inp;
	end
	end

	booth_mult PA0(PA[0],inp_list[0],h[0]);		
	booth_mult PA1(PA[1],inp_list[1],h[1]);		
	booth_mult PA2(PA[2],inp_list[2],h[2]);		
	booth_mult PA3(PA[3],inp_list[3],h[3]);		
	booth_mult PA4(PA[4],inp_list[4],h[4]);		
	booth_mult PA5(PA[5],inp_list[5],h[5]);		
	booth_mult PA6(PA[6],inp_list[6],h[6]);		
	booth_mult PA7(PA[7],inp_list[7],h[7]);		
	booth_mult PA8(PA[8],inp_list[8],h[8]);		
	booth_mult PA9(PA[9],inp_list[9],h[9]);		
	booth_mult PAA(PA[10],inp_list[10],h[10]);		
	booth_mult PAB(PA[11],inp_list[11],h[11]);		
	booth_mult PAC(PA[12],inp_list[12],h[12]);		
	booth_mult PAD(PA[13],inp_list[13],h[13]);		

		always @ (posedge clk, posedge reset) begin
		if (reset) begin
			outp <= 0;
		end else begin
             outp_temp <= ({{4{PA[0][15]}},PA[0]}+{{4{PA[1][15]}},PA[1]}+{{4{PA[2][15]}},PA[2]}+{{4{PA[3][15]}},PA[3]}+{{4{PA[4][15]}},PA[4]}+{{4{PA[5][15]}},PA[5]}+{{4{PA[6][15]}},PA[6]}+{{4{PA[7][15]}},PA[7]}+{{4{PA[8][15]}},PA[8]}+{{4{PA[9][15]}},PA[9]}+{{4{PA[10][15]}},PA[10]}+{{4{PA[11][15]}},PA[11]}+{{4{PA[12][15]}},PA[12]}+{{4{PA[13][15]}},PA[13]});

			outp <= outp_temp[14:7];
		end
		end
endmodule

assignment_4/fir_tb.v
module fir_tb();
    
    reg  [7:0] binary_in[0:255];
    reg  [7:0] binary_out[0:255];
    wire [7:0] outp;
    reg  [7:0] inp;
    reg  [7:0] exp_out;
    reg  [7:0] i;
    reg  reset;
    reg  clk;
    
    initial begin
	$dumpfile("fir.vcd");
	$dumpvars(0, fir_tb);
        i  <= 0;
        clk  <= 0;
        reset  <= 1;
        #50 reset <= 0;
	
        $readmemb("input.list", binary_in);
        $readmemb("output.list", binary_out);

	#3000 $finish;
    end
    
    always #5 clk = ~clk;
    
    fir f1(clk,reset,inp,outp);
    
    always @(posedge clk) begin
       if(reset == 0)begin
          inp     <= binary_in[i];
          exp_out <= binary_out[i];
          i       <= i+1;
       end
    end

endmodule

assignment_4/working/fir/fir.vcd
$date
	Tue Mar 18 15:21:37 2014
$end
$version
	Icarus Verilog
$end
$timescale
	1s
$end
$scope module fir_tb $end
$var wire 8 ! outp [7:0] $end
$var reg 1 " clk $end
$var reg 8 # exp_out [7:0] $end
$var reg 8 $ i [7:0] $end
$var reg 8 % inp [7:0] $end
$var reg 1 & reset $end
$scope module f1 $end
$var wire 1 ' clk $end
$var wire 8 ( inp [7:0] $end
$var wire 1 ) reset $end
$var reg 8 * outp [7:0] $end
$var reg 20 + outp_temp [19:0] $end
$scope module PA0 $end
$var wire 16 , PP1 [15:0] $end
$var wire 16 - PP2 [15:0] $end
$var wire 16 . PP3 [15:0] $end
$var wire 16 / PP4 [15:0] $end
$var wire 8 0 a [7:0] $end
$var wire 8 1 b [7:0] $end
$var reg 16 2 p [15:0] $end
$scope module booth1 $end
$var wire 8 3 A [7:0] $end
$var wire 3 4 B_segment [2:0] $end
$var reg 16 5 A_extended [15:0] $end
$var reg 16 6 PP [15:0] $end
$upscope $end
$scope module booth2 $end
$var wire 8 7 A [7:0] $end
$var wire 3 8 B_segment [2:0] $end
$var reg 16 9 A_extended [15:0] $end
$var reg 16 : PP [15:0] $end
$upscope $end
$scope module booth3 $end
$var wire 8 ; A [7:0] $end
$var wire 3 < B_segment [2:0] $end
$var reg 16 = A_extended [15:0] $end
$var reg 16 > PP [15:0] $end
$upscope $end
$scope module booth4 $end
$var wire 8 ? A [7:0] $end
$var wire 3 @ B_segment [2:0] $end
$var reg 16 A A_extended [15:0] $end
$var reg 16 B PP [15:0] $end
$upscope $end
$upscope $end
$scope module PA1 $end
$var wire 16 C PP1 [15:0] $end
$var wire 16 D PP2 [15:0] $end
$var wire 16 E PP3 [15:0] $end
$var wire 16 F PP4 [15:0] $end
$var wire 8 G a [7:0] $end
$var wire 8 H b [7:0] $end
$var reg 16 I p [15:0] $end
$scope module booth1 $end
$var wire 8 J A [7:0] $end
$var wire 3 K B_segment [2:0] $end
$var reg 16 L A_extended [15:0] $end
$var reg 16 M PP [15:0] $end
$upscope $end
$scope module booth2 $end
$var wire 8 N A [7:0] $end
$var wire 3 O B_segment [2:0] $end
$var reg 16 P A_extended [15:0] $end
$var reg 16 Q PP [15:0] $end
$upscope $end
$scope module booth3 $end
$var wire 8 R A [7:0] $end
$var wire 3 S B_segment [2:0] $end
$var reg 16 T A_extended [15:0] $end
$var reg 16 U PP [15:0] $end
$upscope $end
$scope module booth4 $end
$var wire 8 V A [7:0] $end
$var wire 3 W B_segment [2:0] $end
$var reg 16 X A_extended [15:0] $end
$var reg 16 Y PP [15:0] $end
$upscope $end
$upscope $end
$scope module PA2 $end
$var wire 16 Z PP1 [15:0] $end
$var wire 16 [ PP2 [15:0] $end
$var wire 16 \ PP3 [15:0] $end
$var wire 16 ] PP4 [15:0] $end
$var wire 8 ^ a [7:0] $end
$var wire 8 _ b [7:0] $end
$var reg 16 ` p [15:0] $end
$scope module booth1 $end
$var wire 8 a A [7:0] $end
$var wire 3 b B_segment [2:0] $end
$var reg 16 c A_extended [15:0] $end
$var reg 16 d PP [15:0] $end
$upscope $end
$scope module booth2 $end
$var wire 8 e A [7:0] $end
$var wire 3 f B_segment [2:0] $end
$var reg 16 g A_extended [15:0] $end
$var reg 16 h PP [15:0] $end
$upscope $end
$scope module booth3 $end
$var wire 8 i A [7:0] $end
$var wire 3 j B_segment [2:0] $end
$var reg 16 k A_extended [15:0] $end
$var reg 16 l PP [15:0] $end
$upscope $end
$scope module booth4 $end
$var wire 8 m A [7:0] $end
$var wire 3 n B_segment [2:0] $end
$var reg 16 o A_extended [15:0] $end
$var reg 16 p PP [15:0] $end
$upscope $end
$upscope $end
$scope module PA3 $end
$var wire 16 q PP1 [15:0] $end
$var wire 16 r PP2 [15:0] $end
$var wire 16 s PP3 [15:0] $end
$var wire 16 t PP4 [15:0] $end
$var wire 8 u a [7:0] $end
$var wire 8 v b [7:0] $end
$var reg 16 w p [15:0] $end
$scope module booth1 $end
$var wire 8 x A [7:0] $end
$var wire 3 y B_segment [2:0] $end
$var reg 16 z A_extended [15:0] $end
$var reg 16 { PP [15:0] $end
$upscope $end
$scope module booth2 $end
$var wire 8 | A [7:0] $end
$var wire 3 } B_segment [2:0] $end
$var reg 16 ~ A_extended [15:0] $end
$var reg 16 !" PP [15:0] $end
$upscope $end
$scope module booth3 $end
$var wire 8 "" A [7:0] $end
$var wire 3 #" B_segment [2:0] $end
$var reg 16 $" A_extended [15:0] $end
$var reg 16 %" PP [15:0] $end
$upscope $end
$scope module booth4 $end
$var wire 8 &" A [7:0] $end
$var wire 3 '" B_segment [2:0] $end
$var reg 16 (" A_extended [15:0] $end
$var reg 16 )" PP [15:0] $end
$upscope $end
$upscope $end
$scope module PA4 $end
$var wire 16 *" PP1 [15:0] $end
$var wire 16 +" PP2 [15:0] $end
$var wire 16 ," PP3 [15:0] $end
$var wire 16 -" PP4 [15:0] $end
$var wire 8 ." a [7:0] $end
$var wire 8 /" b [7:0] $end
$var reg 16 0" p [15:0] $end
$scope module booth1 $end
$var wire 8 1" A [7:0] $end
$var wire 3 2" B_segment [2:0] $end
$var reg 16 3" A_extended [15:0] $end
$var reg 16 4" PP [15:0] $end
$upscope $end
$scope module booth2 $end
$var wire 8 5" A [7:0] $end
$var wire 3 6" B_segment [2:0] $end
$var reg 16 7" A_extended [15:0] $end
$var reg 16 8" PP [15:0] $end
$upscope $end
$scope module booth3 $end
$var wire 8 9" A [7:0] $end
$var wire 3 :" B_segment [2:0] $end
$var reg 16 ;" A_extended [15:0] $end
$var reg 16 <" PP [15:0] $end
$upscope $end
$scope module booth4 $end
$var wire 8 =" A [7:0] $end
$var wire 3 >" B_segment [2:0] $end
$var reg 16 ?" A_extended [15:0] $end
$var reg 16 @" PP [15:0] $end
$upscope $end
$upscope $end
$scope module PA5 $end
$var wire 16 A" PP1 [15:0] $end
$var wire 16 B" PP2 [15:0] $end
$var wire 16 C" PP3 [15:0] $end
$var wire 16 D" PP4 [15:0] $end
$var wire 8 E" a [7:0] $end
$var wire 8 F" b [7:0] $end
$var reg 16 G" p [15:0] $end
$scope module booth1 $end
$var wire 8 H" A [7:0] $end
$var wire 3 I" B_segment [2:0] $end
$var reg 16 J" A_extended [15:0] $end
$var reg 16 K" PP [15:0] $end
$upscope $end
$scope module booth2 $end
$var wire 8 L" A [7:0] $end
$var wire 3 M" B_segment [2:0] $end
$var reg 16 N" A_extended [15:0] $end
$var reg 16 O" PP [15:0] $end
$upscope $end
$scope module booth3 $end
$var wire 8 P" A [7:0] $end
$var wire 3 Q" B_segment [2:0] $end
$var reg 16 R" A_extended [15:0] $end
$var reg 16 S" PP [15:0] $end
$upscope $end
$scope module booth4 $end
$var wire 8 T" A [7:0] $end
$var wire 3 U" B_segment [2:0] $end
$var reg 16 V" A_extended [15:0] $end
$var reg 16 W" PP [15:0] $end
$upscope $end
$upscope $end
$scope module PA6 $end
$var wire 16 X" PP1 [15:0] $end
$var wire 16 Y" PP2 [15:0] $end
$var wire 16 Z" PP3 [15:0] $end
$var wire 16 [" PP4 [15:0] $end
$var wire 8 \" a [7:0] $end
$var wire 8 ]" b [7:0] $end
$var reg 16 ^" p [15:0] $end
$scope module booth1 $end
$var wire 8 _" A [7:0] $end
$var wire 3 `" B_segment [2:0] $end
$var reg 16 a" A_extended [15:0] $end
$var reg 16 b" PP [15:0] $end
$upscope $end
$scope module booth2 $end
$var wire 8 c" A [7:0] $end
$var wire 3 d" B_segment [2:0] $end
$var reg 16 e" A_extended [15:0] $end
$var reg 16 f" PP [15:0] $end
$upscope $end
$scope module booth3 $end
$var wire 8 g" A [7:0] $end
$var wire 3 h" B_segment [2:0] $end
$var reg 16 i" A_extended [15:0] $end
$var reg 16 j" PP [15:0] $end
$upscope $end
$scope module booth4 $end
$var wire 8 k" A [7:0] $end
$var wire 3 l" B_segment [2:0] $end
$var reg 16 m" A_extended [15:0] $end
$var reg 16 n" PP [15:0] $end
$upscope $end
$upscope $end
$scope module PA7 $end
$var wire 16 o" PP1 [15:0] $end
$var wire 16 p" PP2 [15:0] $end
$var wire 16 q" PP3 [15:0] $end
$var wire 16 r" PP4 [15:0] $end
$var wire 8 s" a [7:0] $end
$var wire 8 t" b [7:0] $end
$var reg 16 u" p [15:0] $end
$scope module booth1 $end
$var wire 8 v" A [7:0] $end
$var wire 3 w" B_segment [2:0] $end
$var reg 16 x" A_extended [15:0] $end
$var reg 16 y" PP [15:0] $end
$upscope $end
$scope module booth2 $end
$var wire 8 z" A [7:0] $end
$var wire 3 {" B_segment [2:0] $end
$var reg 16 |" A_extended [15:0] $end
$var reg 16 }" PP [15:0] $end
$upscope $end
$scope module booth3 $end
$var wire 8 ~" A [7:0] $end
$var wire 3 !# B_segment [2:0] $end
$var reg 16 "# A_extended [15:0] $end
$var reg 16 ## PP [15:0] $end
$upscope $end
$scope module booth4 $end
$var wire 8 $# A [7:0] $end
$var wire 3 %# B_segment [2:0] $end
$var reg 16 &# A_extended [15:0] $end
$var reg 16 '# PP [15:0] $end
$upscope $end
$upscope $end
$scope module PA8 $end
$var wire 16 (# PP1 [15:0] $end
$var wire 16 )# PP2 [15:0] $end
$var wire 16 *# PP3 [15:0] $end
$var wire 16 +# PP4 [15:0] $end
$var wire 8 ,# a [7:0] $end
$var wire 8 -# b [7:0] $end
$var reg 16 .# p [15:0] $end
$scope module booth1 $end
$var wire 8 /# A [7:0] $end
$var wire 3 0# B_segment [2:0] $end
$var reg 16 1# A_extended [15:0] $end
$var reg 16 2# PP [15:0] $end
$upscope $end
$scope module booth2 $end
$var wire 8 3# A [7:0] $end
$var wire 3 4# B_segment [2:0] $end
$var reg 16 5# A_extended [15:0] $end
$var reg 16 6# PP [15:0] $end
$upscope $end
$scope module booth3 $end
$var wire 8 7# A [7:0] $end
$var wire 3 8# B_segment [2:0] $end
$var reg 16 9# A_extended [15:0] $end
$var reg 16 :# PP [15:0] $end
$upscope $end
$scope module booth4 $end
$var wire 8 ;# A [7:0] $end
$var wire 3 <# B_segment [2:0] $end
$var reg 16 =# A_extended [15:0] $end
$var reg 16 ># PP [15:0] $end
$upscope $end
$upscope $end
$scope module PA9 $end
$var wire 16 ?# PP1 [15:0] $end
$var wire 16 @# PP2 [15:0] $end
$var wire 16 A# PP3 [15:0] $end
$var wire 16 B# PP4 [15:0] $end
$var wire 8 C# a [7:0] $end
$var wire 8 D# b [7:0] $end
$var reg 16 E# p [15:0] $end
$scope module booth1 $end
$var wire 8 F# A [7:0] $end
$var wire 3 G# B_segment [2:0] $end
$var reg 16 H# A_extended [15:0] $end
$var reg 16 I# PP [15:0] $end
$upscope $end
$scope module booth2 $end
$var wire 8 J# A [7:0] $end
$var wire 3 K# B_segment [2:0] $end
$var reg 16 L# A_extended [15:0] $end
$var reg 16 M# PP [15:0] $end
$upscope $end
$scope module booth3 $end
$var wire 8 N# A [7:0] $end
$var wire 3 O# B_segment [2:0] $end
$var reg 16 P# A_extended [15:0] $end
$var reg 16 Q# PP [15:0] $end
$upscope $end
$scope module booth4 $end
$var wire 8 R# A [7:0] $end
$var wire 3 S# B_segment [2:0] $end
$var reg 16 T# A_extended [15:0] $end
$var reg 16 U# PP [15:0] $end
$upscope $end
$upscope $end
$scope module PAA $end
$var wire 16 V# PP1 [15:0] $end
$var wire 16 W# PP2 [15:0] $end
$var wire 16 X# PP3 [15:0] $end
$var wire 16 Y# PP4 [15:0] $end
$var wire 8 Z# a [7:0] $end
$var wire 8 [# b [7:0] $end
$var reg 16 \# p [15:0] $end
$scope module booth1 $end
$var wire 8 ]# A [7:0] $end
$var wire 3 ^# B_segment [2:0] $end
$var reg 16 _# A_extended [15:0] $end
$var reg 16 `# PP [15:0] $end
$upscope $end
$scope module booth2 $end
$var wire 8 a# A [7:0] $end
$var wire 3 b# B_segment [2:0] $end
$var reg 16 c# A_extended [15:0] $end
$var reg 16 d# PP [15:0] $end
$upscope $end
$scope module booth3 $end
$var wire 8 e# A [7:0] $end
$var wire 3 f# B_segment [2:0] $end
$var reg 16 g# A_extended [15:0] $end
$var reg 16 h# PP [15:0] $end
$upscope $end
$scope module booth4 $end
$var wire 8 i# A [7:0] $end
$var wire 3 j# B_segment [2:0] $end
$var reg 16 k# A_extended [15:0] $end
$var reg 16 l# PP [15:0] $end
$upscope $end
$upscope $end
$scope module PAB $end
$var wire 16 m# PP1 [15:0] $end
$var wire 16 n# PP2 [15:0] $end
$var wire 16 o# PP3 [15:0] $end
$var wire 16 p# PP4 [15:0] $end
$var wire 8 q# a [7:0] $end
$var wire 8 r# b [7:0] $end
$var reg 16 s# p [15:0] $end
$scope module booth1 $end
$var wire 8 t# A [7:0] $end
$var wire 3 u# B_segment [2:0] $end
$var reg 16 v# A_extended [15:0] $end
$var reg 16 w# PP [15:0] $end
$upscope $end
$scope module booth2 $end
$var wire 8 x# A [7:0] $end
$var wire 3 y# B_segment [2:0] $end
$var reg 16 z# A_extended [15:0] $end
$var reg 16 {# PP [15:0] $end
$upscope $end
$scope module booth3 $end
$var wire 8 |# A [7:0] $end
$var wire 3 }# B_segment [2:0] $end
$var reg 16 ~# A_extended [15:0] $end
$var reg 16 !$ PP [15:0] $end
$upscope $end
$scope module booth4 $end
$var wire 8 "$ A [7:0] $end
$var wire 3 #$ B_segment [2:0] $end
$var reg 16 $$ A_extended [15:0] $end
$var reg 16 %$ PP [15:0] $end
$upscope $end
$upscope $end
$scope module PAC $end
$var wire 16 &$ PP1 [15:0] $end
$var wire 16 '$ PP2 [15:0] $end
$var wire 16 ($ PP3 [15:0] $end
$var wire 16 )$ PP4 [15:0] $end
$var wire 8 *$ a [7:0] $end
$var wire 8 +$ b [7:0] $end
$var reg 16 ,$ p [15:0] $end
$scope module booth1 $end
$var wire 8 -$ A [7:0] $end
$var wire 3 .$ B_segment [2:0] $end
$var reg 16 /$ A_extended [15:0] $end
$var reg 16 0$ PP [15:0] $end
$upscope $end
$scope module booth2 $end
$var wire 8 1$ A [7:0] $end
$var wire 3 2$ B_segment [2:0] $end
$var reg 16 3$ A_extended [15:0] $end
$var reg 16 4$ PP [15:0] $end
$upscope $end
$scope module booth3 $end
$var wire 8 5$ A [7:0] $end
$var wire 3 6$ B_segment [2:0] $end
$var reg 16 7$ A_extended [15:0] $end
$var reg 16 8$ PP [15:0] $end
$upscope $end
$scope module booth4 $end
$var wire 8 9$ A [7:0] $end
$var wire 3 :$ B_segment [2:0] $end
$var reg 16 ;$ A_extended [15:0] $end
$var reg 16 <$ PP [15:0] $end
$upscope $end
$upscope $end
$scope module PAD $end
$var wire 16 =$ PP1 [15:0] $end
$var wire 16 >$ PP2 [15:0] $end
$var wire 16 ?$ PP3 [15:0] $end
$var wire 16 @$ PP4 [15:0] $end
$var wire 8 A$ a [7:0] $end
$var wire 8 B$ b [7:0] $end
$var reg 16 C$ p [15:0] $end
$scope module booth1 $end
$var wire 8 D$ A [7:0] $end
$var wire 3 E$ B_segment [2:0] $end
$var reg 16 F$ A_extended [15:0] $end
$var reg 16 G$ PP [15:0] $end
$upscope $end
$scope module booth2 $end
$var wire 8 H$ A [7:0] $end
$var wire 3 I$ B_segment [2:0] $end
$var reg 16 J$ A_extended [15:0] $end
$var reg 16 K$ PP [15:0] $end
$upscope $end
$scope module booth3 $end
$var wire 8 L$ A [7:0] $end
$var wire 3 M$ B_segment [2:0] $end
$var reg 16 N$ A_extended [15:0] $end
$var reg 16 O$ PP [15:0] $end
$upscope $end
$scope module booth4 $end
$var wire 8 P$ A [7:0] $end
$var wire 3 Q$ B_segment [2:0] $end
$var reg 16 R$ A_extended [15:0] $end
$var reg 16 S$ PP [15:0] $end
$upscope $end
$upscope $end
$upscope $end
$upscope $end
$enddefinitions $end
#0
$dumpvars
b0 S$
b0 R$
b0 Q$
b0 P$
b0 O$
b0 N$
b0 M$
b0 L$
b0 K$
b0 J$
b0 I$
b0 H$
b0 G$
b0 F$
b0 E$
b0 D$
b0 C$
b0 B$
b0 A$
b0 @$
b0 ?$
b0 >$
b0 =$
b0 <$
b0 ;$
b111 :$
b0 9$
b0 8$
b0 7$
b111 6$
b0 5$
b0 4$
b0 3$
b101 2$
b0 1$
b0 0$
b0 /$
b110 .$
b0 -$
b0 ,$
b11111011 +$
b0 *$
b0 )$
b0 ($
b0 '$
b0 &$
b0 %$
b0 $$
b111 #$
b0 "$
b0 !$
b0 ~#
b111 }#
b0 |#
b0 {#
b0 z#
b101 y#
b0 x#
b0 w#
b0 v#
b110 u#
b0 t#
b0 s#
b11111011 r#
b0 q#
b0 p#
b0 o#
b0 n#
b0 m#
b0 l#
b0 k#
b111 j#
b0 i#
b0 h#
b0 g#
b111 f#
b0 e#
b0 d#
b0 c#
b111 b#
b0 a#
b0 `#
b0 _#
b110 ^#
b0 ]#
b0 \#
b11111111 [#
b0 Z#
b0 Y#
b0 X#
b0 W#
b0 V#
b0 U#
b0 T#
b0 S#
b0 R#
b0 Q#
b0 P#
b1 O#
b0 N#
b0 M#
b0 L#
b101 K#
b0 J#
b0 I#
b0 H#
b100 G#
b0 F#
b0 E#
b1010 D#
b0 C#
b0 B#
b0 A#
b0 @#
b0 ?#
b0 >#
b0 =#
b0 <#
b0 ;#
b0 :#
b0 9#
b11 8#
b0 7#
b0 6#
b0 5#
b100 4#
b0 3#
b0 2#
b0 1#
b10 0#
b0 /#
b0 .#
b11001 -#
b0 ,#
b0 +#
b0 *#
b0 )#
b0 (#
b0 '#
b0 &#
b1 %#
b0 $#
b0 ##
b0 "#
b100 !#
b0 ~"
b0 }"
b0 |"
b10 {"
b0 z"
b0 y"
b0 x"
b0 w"
b0 v"
b0 u"
b100100 t"
b0 s"
b0 r"
b0 q"
b0 p"
b0 o"
b0 n"
b0 m"
b1 l"
b0 k"
b0 j"
b0 i"
b100 h"
b0 g"
b0 f"
b0 e"
b10 d"
b0 c"
b0 b"
b0 a"
b0 `"
b0 _"
b0 ^"
b100100 ]"
b0 \"
b0 ["
b0 Z"
b0 Y"
b0 X"
b0 W"
b0 V"
b0 U"
b0 T"
b0 S"
b0 R"
b11 Q"
b0 P"
b0 O"
b0 N"
b100 M"
b0 L"
b0 K"
b0 J"
b10 I"
b0 H"
b0 G"
b11001 F"
b0 E"
b0 D"
b0 C"
b0 B"
b0 A"
b0 @"
b0 ?"
b0 >"
b0 ="
b0 <"
b0 ;"
b1 :"
b0 9"
b0 8"
b0 7"
b101 6"
b0 5"
b0 4"
b0 3"
b100 2"
b0 1"
b0 0"
b1010 /"
b0 ."
b0 -"
b0 ,"
b0 +"
b0 *"
b0 )"
b0 ("
b111 '"
b0 &"
b0 %"
b0 $"
b111 #"
b0 ""
b0 !"
b0 ~
b111 }
b0 |
b0 {
b0 z
b110 y
b0 x
b0 w
b11111111 v
b0 u
b0 t
b0 s
b0 r
b0 q
b0 p
b0 o
b111 n
b0 m
b0 l
b0 k
b111 j
b0 i
b0 h
b0 g
b101 f
b0 e
b0 d
b0 c
b110 b
b0 a
b0 `
b11111011 _
b0 ^
b0 ]
b0 \
b0 [
b0 Z
b0 Y
b0 X
b111 W
b0 V
b0 U
b0 T
b111 S
b0 R
b0 Q
b0 P
b101 O
b0 N
b0 M
b0 L
b110 K
b0 J
b0 I
b11111011 H
b0 G
b0 F
b0 E
b0 D
b0 C
b0 B
b0 A
b0 @
b0 ?
b0 >
b0 =
b0 <
b0 ;
b0 :
b0 9
b0 8
b0 7
b0 6
b0 5
b0 4
b0 3
b0 2
b0 1
b0 0
b0 /
b0 .
b0 -
b0 ,
bx +
b0 *
1)
bx (
0'
1&
bx %
b0 $
bx #
0"
b0 !
$end
#5
1"
1'
#10
0"
0'
#15
1"
1'
#20
0"
0'
#25
1"
1'
#30
0"
0'
#35
1"
1'
#40
0"
0'
#45
1"
1'
#50
0&
0)
0"
0'
#55
bx A
bx =
bx 9
bx 5
bx 0
bx 3
bx 7
bx ;
bx ?
bx *
bx !
b0 +
b1 $
b0 #
b0 %
b0 (
1"
1'
#60
0"
0'
#65
bx I
bx Q
bx D
bx M
bx C
b0 A
b0 =
b0 9
b0 5
bx X
bx T
bx P
bx L
b0 *
b0 !
b0 0
b0 3
b0 7
b0 ;
b0 ?
bx G
bx J
bx N
bx R
bx V
b10 $
b11111110 #
b1010100 %
b1010100 (
1"
1'
#70
0"
0'
#75
b0 I
bx `
b0 Q
b0 D
b0 M
b0 C
bx h
bx [
bx d
bx Z
b1010100 A
b1010100 =
b1010100 9
b1010100 5
b0 X
b0 T
b0 P
b0 L
bx o
bx k
bx g
bx c
b1010100 0
b1010100 3
b1010100 7
b1010100 ;
b1010100 ?
b0 G
b0 J
b0 N
b0 R
b0 V
bx ^
bx a
bx e
bx i
bx m
bx +
b11 $
b1 #
b1010 %
b1010 (
1"
1'
#80
0"
0'
#85
b1111111001011100 I
b0 `
bx w
b1111111110101100 Q
b1111111110101100 D
b1111111110101100 M
b1111111110101100 C
b0 h
b0 [
b0 d
b0 Z
bx {
bx q
b1010 A
b1010 =
b1010 9
b1010 5
b1010100 X
b1010100 T
b1010100 P
b1010100 L
b0 o
b0 k
b0 g
b0 c
bx ("
bx $"
bx ~
bx z
bx *
bx !
b1010 0
b1010 3
b1010 7
b1010 ;
b1010 ?
b1010100 G
b1010100 J
b1010100 N
b1010100 R
b1010100 V
b0 ^
b0 a
b0 e
b0 i
b0 m
bx u
bx x
bx |
bx ""
bx &"
b100 $
b11 #
b1101 %
b1101 (
1"
1'
#90
0"
0'
#95
b1111111111001110 I
b1111111001011100 `
b0 w
bx 0"
b1111111111110110 Q
b1111111111110110 D
b1111111111110110 M
b1111111111110110 C
b1111111110101100 h
b1111111110101100 [
b1111111110101100 d
b1111111110101100 Z
b0 {
b0 q
bx <"
bx ,"
bx 8"
bx +"
bx0 4"
bx0 *"
b1101 A
b1101 =
b1101 9
b1101 5
b1010 X
b1010 T
b1010 P
b1010 L
b1010100 o
b1010100 k
b1010100 g
b1010100 c
b0 ("
b0 $"
b0 ~
b0 z
bx ?"
bx ;"
bx 7"
bx 3"
b1101 0
b1101 3
b1101 7
b1101 ;
b1101 ?
b1010 G
b1010 J
b1010 N
b1010 R
b1010 V
b1010100 ^
b1010100 a
b1010100 e
b1010100 i
b1010100 m
b0 u
b0 x
b0 |
b0 ""
b0 &"
bx ."
bx 1"
bx 5"
bx 9"
bx ="
b101 $
b0 #
b1111000 %
b1111000 (
1"
1'
#100
0"
0'
#105
b1111111110111111 I
b1111111111001110 `
b1111111110101100 w
b0 0"
bx G"
b1111111111110011 Q
b1111111111110011 D
b1111111111110011 M
b1111111111110011 C
b1111111111110110 h
b1111111111110110 [
b1111111111110110 d
b1111111111110110 Z
b1111111110101100 {
b1111111110101100 q
b0 <"
b0 ,"
b0 8"
b0 +"
b0 4"
b0 *"
bx0 S"
bx0 C"
bx0 O"
bx0 B"
bx K"
bx A"
b1111000 A
b1111000 =
b1111000 9
b1111000 5
b1101 X
b1101 T
b1101 P
b1101 L
b1010 o
b1010 k
b1010 g
b1010 c
b1010100 ("
b1010100 $"
b1010100 ~
b1010100 z
b0 ?"
b0 ;"
b0 7"
b0 3"
bx V"
bx R"
bx N"
bx J"
b1111000 0
b1111000 3
b1111000 7
b1111000 ;
b1111000 ?
b1101 G
b1101 J
b1101 N
b1101 R
b1101 V
b1010 ^
b1010 a
b1010 e
b1010 i
b1010 m
b1010100 u
b1010100 x
b1010100 |
b1010100 ""
b1010100 &"
b0 ."
b0 1"
b0 5"
b0 9"
b0 ="
bx E"
bx H"
bx L"
bx P"
bx T"
b110 $
b11111010 #
b1001011 %
b1001011 (
1"
1'
#110
0"
0'
